aspose_tasks_cloud-25.11.0.dist-info/licenses/LICENSE
asposetaskscloud/__init__.py
asposetaskscloud/api_client.py
asposetaskscloud/configuration.py
asposetaskscloud/rest.py
asposetaskscloud/api/__init__.py
asposetaskscloud/api/tasks_api.py
asposetaskscloud/models/__init__.py
asposetaskscloud/models/aspose_response.py
asposetaskscloud/models/assignment_baseline.py
asposetaskscloud/models/assignment_item.py
asposetaskscloud/models/assignment_item_response.py
asposetaskscloud/models/assignment_items.py
asposetaskscloud/models/assignment_items_response.py
asposetaskscloud/models/assignment_response.py
asposetaskscloud/models/assignments_response.py
asposetaskscloud/models/background_pattern.py
asposetaskscloud/models/baseline.py
asposetaskscloud/models/baseline_type.py
asposetaskscloud/models/booking_type.py
asposetaskscloud/models/calculation_mode.py
asposetaskscloud/models/calculation_type.py
asposetaskscloud/models/calendar.py
asposetaskscloud/models/calendar_exception.py
asposetaskscloud/models/calendar_exception_type.py
asposetaskscloud/models/calendar_exceptions_response.py
asposetaskscloud/models/calendar_item.py
asposetaskscloud/models/calendar_item_response.py
asposetaskscloud/models/calendar_items.py
asposetaskscloud/models/calendar_items_response.py
asposetaskscloud/models/calendar_response.py
asposetaskscloud/models/calendar_work_weeks_response.py
asposetaskscloud/models/colors.py
asposetaskscloud/models/confidence_level.py
asposetaskscloud/models/constraint_type.py
asposetaskscloud/models/cost_accrual_type.py
asposetaskscloud/models/custom_field_type.py
asposetaskscloud/models/day_of_week.py
asposetaskscloud/models/day_type.py
asposetaskscloud/models/disc_usage.py
asposetaskscloud/models/document_properties.py
asposetaskscloud/models/document_properties_response.py
asposetaskscloud/models/document_property.py
asposetaskscloud/models/document_property_response.py
asposetaskscloud/models/duration.py
asposetaskscloud/models/earned_value_method_type.py
asposetaskscloud/models/element_type.py
aspose_tasks_cloud-25.11.0.dist-info/METADATA
aspose_tasks_cloud-25.11.0.dist-info/WHEEL
aspose_tasks_cloud-25.11.0.dist-info/top_level.txt
aspose_tasks_cloud-25.11.0.dist-info/RECORD
