Metadata-Version: 2.4
Name: aspose-tasks-cloud
Version: 25.11.0
Summary: Aspose.Tasks Cloud API Reference
Home-page: https://github.com/aspose-tasks-cloud/aspose-tasks-cloud-python
Author: Ivan Andreychikov
Author-email: ivan.andreychikov@aspose.com
Keywords: aspose,python,aspose cloud,microsoft project,mpp,primavera,microsoft project server,microsoft project online
Classifier: Development Status :: 5 - Production/Stable
Classifier: Intended Audience :: Developers
Classifier: Topic :: Office/Business :: Office Suites
Classifier: Topic :: Software Development :: Libraries
Classifier: License :: OSI Approved :: MIT License
Classifier: Programming Language :: Python :: 2.7
Classifier: Programming Language :: Python :: 3.4
Classifier: Programming Language :: Python :: 3.5
Classifier: Programming Language :: Python :: 3.6
Classifier: Programming Language :: Python :: 3.7
License-File: LICENSE
Requires-Dist: urllib3>=1.16
Requires-Dist: six>=1.10
Requires-Dist: certifi
Requires-Dist: python-dateutil
Dynamic: author
Dynamic: author-email
Dynamic: classifier
Dynamic: description
Dynamic: description-content-type
Dynamic: home-page
Dynamic: keywords
Dynamic: license-file
Dynamic: requires-dist
Dynamic: summary
